{
  "version": "0.0.1",
  "catchAll": {
    "next": []
  },
  "startNode": "check-if-extracted",
  "skillData": {
    "retryAttempts": 3,
    "contentElement": "builtin_text-H9oobk",
    "notFoundElement": "builtin_text-THLu1a",
    "turnExpiry": 3,
    "intent": "cust-details",
    "slotName": "phone",
    "entities": [
      "phoneNumber"
    ]
  },
  "nodes": [
    {
      "name": "slot-extract",
      "onEnter": [
        "say #!builtin_text-H9oobk {}"
      ],
      "onReceive": [
        "basic-skills/slot_fill {\"slotName\":\"phone\",\"entities\":\"phoneNumber\", \"turnExpiry\":3}"
      ],
      "next": [
        {
          "condition": "session.slots['phone'] && (temp.valid === undefined || temp.valid == \"true\")",
          "node": "extracted"
        },
        {
          "condition": "true",
          "node": "not-extracted"
        }
      ],
      "id": "236886"
    },
    {
      "name": "extracted",
      "onEnter": [
        "builtin/setVariable {\"type\":\"temp\",\"name\":\"extracted\",\"value\":\"true\"}"
      ],
      "next": [
        {
          "condition": "true",
          "node": "#"
        }
      ],
      "id": "048246"
    },
    {
      "name": "not-extracted",
      "onEnter": [
        "basic-skills/slot_not_found {\"retryAttempts\":\"3\"}",
        "say #!builtin_text-THLu1a {}",
        "builtin/setVariable {\"type\":\"temp\",\"name\":\"valid\",\"value\": \"true\"}"
      ],
      "onReceive": [
        "basic-skills/slot_fill {\"slotName\":\"phone\",\"entities\":\"phoneNumber\", \"turnExpiry\":3}"
      ],
      "next": [
        {
          "condition": "session.slots['phone'] && (temp.valid === undefined || temp.valid == \"true\")",
          "node": "extracted"
        },
        {
          "condition": "temp.notExtracted == \"true\"",
          "node": "#"
        },
        {
          "condition": "true",
          "node": "not-extracted"
        }
      ],
      "id": "994423"
    },
    {
      "name": "check-if-extracted",
      "onEnter": [
        "basic-skills/slot_update_contexts {\"intentName\":\"cust-details\"}"
      ],
      "next": [
        {
          "condition": "session.slots['phone'] !== undefined",
          "node": "already-extracted"
        },
        {
          "condition": "true",
          "node": "slot-extract"
        }
      ],
      "id": "495698"
    },
    {
      "name": "already-extracted",
      "onEnter": [
        "builtin/setVariable {\"type\":\"temp\",\"name\":\"alreadyExtracted\",\"value\":\"true\"}",
        "builtin/setVariable {\"type\":\"temp\",\"name\":\"valid\",\"value\": \"true\"}"
      ],
      "next": [
        {
          "condition": " (temp.valid === undefined || temp.valid == \"true\")",
          "node": "#"
        },
        {
          "condition": "true",
          "node": "slot-extract"
        }
      ],
      "id": "110329"
    }
  ]
}